{"game":{"appId":1793170,"name":"Racine","capsuleUrl":"https://shared.akamai.steamstatic.com/store_item_assets/steam/apps/1793170/header.jpg?t=1727786294","genres":"RPG, Strategy","categories":"Single-player, Steam Achievements, Full controller support, Steam Cloud, Family Sharing","tags":null,"shortDescription":"Racine은 전략 로그라이크 오토배틀러 게임입니다. 카드를 사용해서 영웅의 능력치를 증가시키고 강력한 주문을 시전하세요. 유물과 새 카드를 찾아내서 나만의 플레이 스타일을 만들어 보세요.","shortDescriptionEn":"Racine is an Autobattler Strategy Roguelike. Use your cards to increase your heroes stats or cast powerful spells. Find some artifacts and new cards to develop your own play style.","reviewSummary":"Mixed | 60% | 182 reviews","reviewPercent":60,"reviewCount":182,"developers":"Dark Root Gardeners, Goblinz Studio","publishers":"Goblinz Publishing, Maple Whispering Limited","dlcCount":null,"appType":"game","koreanSupport":true,"koreanSubtitle":true,"koreanAudio":false,"englishSupport":true,"englishSubtitle":true,"englishAudio":false,"releaseStatus":"RELEASED","releaseDate":"2023-11-06T00:00:00.000Z","releaseDateRaw":"6 Nov, 2023"},"dlcList":[],"latest":{"currency":"USD","price":249,"basePrice":999,"discountPercent":75,"discountEnd":"2026-01-22T14:59:59.000Z","recordedAt":"2026-01-11T03:05:55.219Z"},"history":[],"playerHistory":[],"playerLatest":null,"stats":{"average":249,"allTimeLow":249,"basePriceLow":999,"sixMonthLow":249},"reviewHighlights":[{"text":"It's hard to have a reactive parry system when both you and the enemies' attacks queue is really awkward ways. Basically, playing a card cuts incoming...","votes":2}]}