{"game":{"appId":205633,"name":"Tropico 4: Megalopolis DLC","capsuleUrl":"https://shared.akamai.steamstatic.com/store_item_assets/steam/apps/205633/header.jpg?t=1644314730","genres":"Simulation, Strategy","categories":"Single-player, Downloadable Content, Family Sharing","tags":null,"shortDescription":"Build the largest city in the Caribbean on an island with constant influx of immigrants. Deal with problems such as unemployment, over-population and food shortages. Use the Conventillo, a cheap residential building that houses many residents using little space.","shortDescriptionEn":"Build the largest city in the Caribbean on an island with constant influx of immigrants. Deal with problems such as unemployment, over-population and food shortages. Use the Conventillo, a cheap residential building that houses many residents using little space.","reviewSummary":null,"reviewPercent":null,"reviewCount":null,"developers":"Haemimont Games","publishers":"Kalypso Media Digital","dlcCount":null,"appType":"dlc","koreanSupport":false,"koreanSubtitle":false,"koreanAudio":false,"englishSupport":true,"englishSubtitle":true,"englishAudio":true,"releaseStatus":"RELEASED","releaseDate":"2012-11-15T00:00:00.000Z","releaseDateRaw":"15 Nov, 2012"},"dlcList":[],"latest":{"currency":"KRW","price":180000,"basePrice":360000,"discountPercent":50,"discountEnd":null,"recordedAt":"2026-01-11T05:18:51.494Z"},"history":[],"playerHistory":[],"playerLatest":null,"stats":{"average":null,"allTimeLow":180000,"basePriceLow":360000,"sixMonthLow":180000},"reviewHighlights":[]}