{"game":{"appId":3547520,"name":"Ship of Fools - Golden Bay Duo","capsuleUrl":"https://shared.akamai.steamstatic.com/store_item_assets/steam/apps/3547520/846eeb338009e50bd03111804a0b2888a7101840/header.jpg?t=1745510298","genres":"Action, Indie","categories":"Single-player, Multi-player, Co-op, Online Co-op, Shared/Split Screen Co-op, Shared/Split Screen, Downloadable Content, Steam Achievements, Full controller support, Steam Cloud, Remote Play Together, Family Sharing","tags":null,"shortDescription":"The Golden Bay Duo와 함께 돛을 펴고 황금과 영광을 찾아 떠나세요!","shortDescriptionEn":"Set sail for gold and glory with The Golden Bay Duo!","reviewSummary":null,"reviewPercent":null,"reviewCount":null,"developers":"Fika Productions","publishers":"Team17","dlcCount":null,"appType":"dlc","koreanSupport":true,"koreanSubtitle":true,"koreanAudio":false,"englishSupport":true,"englishSubtitle":true,"englishAudio":false,"releaseStatus":"RELEASED","releaseDate":"2025-04-24T00:00:00.000Z","releaseDateRaw":"24 Apr, 2025"},"dlcList":[],"latest":{"currency":"KRW","price":563000,"basePrice":563000,"discountPercent":0,"discountEnd":null,"recordedAt":"2026-01-10T20:53:32.142Z"},"history":[],"playerHistory":[],"playerLatest":null,"stats":{"average":null,"allTimeLow":563000,"basePriceLow":563000,"sixMonthLow":563000},"reviewHighlights":[]}