{"game":{"appId":3848750,"name":"Coincidences?","capsuleUrl":"https://shared.akamai.steamstatic.com/store_item_assets/steam/apps/3848750/c5f380927df70a9739d4ec434df60f876eb2dab3/header.jpg?t=1765752859","genres":"Adventure, Indie","categories":"Single-player, Family Sharing","shortDescription":"갑작스러운 집세 인상으로 숲 속 깊은 곳의 믿기지 않을 만큼 싼 집으로 이사했다. 터무니없는 가격에 직장도 가까워 행운이라 여겼지만, 곧 이곳에 뭔가 문제가 있다는 걸 깨닫게 된다…","shortDescriptionEn":"After a sudden rent hike, you move into a suspiciously cheap house deep in the woods. The price is absurdly low and there’s work nearby—it seems like a stroke of luck. But you soon realize something is seriously wrong with the place...","reviewSummary":null,"reviewPercent":null,"reviewCount":null,"developers":"FogTime","publishers":"FogTime","dlcCount":null,"koreanSupport":true,"koreanSubtitle":true,"koreanAudio":false,"englishSupport":true,"englishSubtitle":true,"englishAudio":false,"releaseStatus":"UPCOMING","releaseDate":"2026-01-01T00:00:00.000Z","releaseDateRaw":"5 Feb, 2026"},"latest":null,"history":[],"playerHistory":[],"playerLatest":null,"stats":{"average":null,"allTimeLow":null,"basePriceLow":null,"sixMonthLow":null},"reviewHighlights":[]}