{"game":{"appId":3919360,"name":"Dig Island","capsuleUrl":"https://shared.akamai.steamstatic.com/store_item_assets/steam/apps/3919360/bfc738f9416b01019475057d778b67fbfaff72ac/header.jpg?t=1767704338","genres":"Adventure, Casual, Indie, Simulation","categories":"Single-player, Multi-player, Co-op, Online Co-op, Steam Achievements, Steam Cloud, Family Sharing","tags":null,"shortDescription":"Dig Island는 4인 협동 굴착 게임입니다. 더 깊이 파고들수록 새로운 자원을 발견하고 장비를 업그레이드하며, 친구들과 함께 비행기를 수리해 섬에서 탈출하세요.","shortDescriptionEn":"Dig Island is a 4-player co-op digging game. As you dig deeper, discover new resources, upgrade your equipment, and work with your friends to repair the plane and escape the island.","reviewSummary":null,"reviewPercent":null,"reviewCount":null,"developers":"FiftyEight Studios","publishers":"FiftyEight Studios","dlcCount":null,"appType":"game","koreanSupport":false,"koreanSubtitle":false,"koreanAudio":false,"englishSupport":true,"englishSubtitle":true,"englishAudio":true,"releaseStatus":"UPCOMING","releaseDate":null,"releaseDateRaw":"Q1 2026"},"dlcList":[],"latest":null,"history":[],"playerHistory":[],"playerLatest":null,"stats":{"average":null,"allTimeLow":null,"basePriceLow":null,"sixMonthLow":null},"reviewHighlights":[]}