{"game":{"appId":1237320,"name":"Sonic Frontiers","capsuleUrl":"https://shared.akamai.steamstatic.com/store_item_assets/steam/apps/1237320/header.jpg?t=1763684832","genres":"액션, 어드벤처","categories":"싱글 플레이어, Steam 도전 과제, 컨트롤러 완벽 지원, Steam 트레이딩 카드, Steam Cloud, 가족 공유","tags":null,"shortDescription":"『소닉 프론티어』는 소닉 특유의 초음속 액션으로 광대한 섬을 자유롭게 누비는 종횡무진 새로운 경지의 액션 어드벤처입니다.","shortDescriptionEn":"Experience Sonic like never before!","reviewSummary":"Very Positive | 90% | 18,544 reviews","reviewPercent":90,"reviewCount":18544,"developers":"Sonic Team","publishers":"SEGA","dlcCount":3,"appType":null,"koreanSupport":true,"koreanSubtitle":true,"koreanAudio":false,"englishSupport":true,"englishSubtitle":true,"englishAudio":true,"releaseStatus":"RELEASED","releaseDate":"2022-01-01T00:00:00.000Z","releaseDateRaw":"7 Nov, 2022"},"dlcList":[],"latest":{"currency":"KRW","price":1494000,"basePrice":4980000,"discountPercent":70,"discountEnd":"2026-01-13T14:59:59.000Z","recordedAt":"2026-01-10T01:21:53.977Z"},"history":[],"playerHistory":[],"playerLatest":null,"stats":{"average":1494000,"allTimeLow":1494000,"basePriceLow":4980000,"sixMonthLow":1494000},"reviewHighlights":[{"text":"[h1]5.4 / 10[/h1] 유입이 줄어드는 프랜차이즈를 부활시키기 위해 변화를 시도했지만, 오픈 월드에 대한 낮은 이해도로 인해 이도 저도 안 된 느낌입니다. 파이널 판타지, 젤다의 전설 같은 동년배들의 성공적인 사례와 비교하면 너무 아쉽습니다. [h1]시원한 보...","votes":18},{"text":"일단 게임은 즐겁게 했습니다만 소닉팬이 아닌 입문자 기준으로 게임을 즐기려면 몇가지 주의점이 필요한 것 같습니다 특히 스피드와 조작, 시점 그리고 게임 난이도 측면에서 게임에 대한 의욕이 많이 줄어들때가 있었습니다 그래서 입문자시면 귀찮더라도 게임옵션에서 어느정도 수정...","votes":3}]}