{"game":{"appId":1689620,"name":"BLEACH Rebirth of Souls","capsuleUrl":"https://shared.akamai.steamstatic.com/store_item_assets/steam/apps/1689620/header.jpg?t=1765454766","genres":"액션","categories":"싱글 플레이어, 멀티플레이어, PvP, 온라인 PvP, 스크린 공유 및 분할 PvP, 공유 및 분할 화면, Steam 도전 과제, 컨트롤러 완벽 지원, Steam Cloud, 가족 공유","shortDescription":"플레이어블 캐릭터 전원이 각성하고 극한의 상황을 뒤집어 역전하는 『BLEACH』의 \"일격필살\" 드라마틱 대전 액션을 체감하라!","shortDescriptionEn":"Awaken the blade within you and reverse your fate in BLEACH Rebirth of Souls! Engage in thrilling battles with powerful sword abilities and characters from this legendary anime franchise.","reviewSummary":"Mostly Positive | 71% | 3,303 reviews","reviewPercent":71,"reviewCount":3303,"developers":"TAMSOFT CORPORATION","publishers":"Bandai Namco Entertainment Inc.","dlcCount":8,"koreanSupport":true,"koreanSubtitle":true,"koreanAudio":false,"englishSupport":true,"englishSubtitle":true,"englishAudio":true,"releaseStatus":"RELEASED","releaseDate":"2025-01-01T00:00:00.000Z","releaseDateRaw":"20 Mar, 2025"},"latest":{"currency":"KRW","price":6980000,"basePrice":6980000,"discountPercent":0,"discountEnd":null,"recordedAt":"2026-01-10T01:21:53.977Z"},"history":[],"playerHistory":[],"playerLatest":null,"stats":{"average":6980000,"allTimeLow":6980000,"basePriceLow":6980000,"sixMonthLow":6980000},"reviewHighlights":[{"text":"입문 장벽이 낮고 집에서 패드로 다른 사람과 같이 하니까 보는 맛도 있고 할만함","votes":1},{"text":"스킬 뽕맛? 좃 됨 그냥. 기술 하나하나가 미쳤음. 블리치 관련 영상매체 중 연출로는 탑급인듯 스크립트 상 대화할 때 조금 짜치는 거 빼고는 최고의 게임 스토리 모드만으로도 즐길 가치가 있다 ㅇㅇ 블리치 팬이라면 세일할 땐 무조건 사셈","votes":0}]}