{"game":{"appId":1809540,"name":"Nine Sols","capsuleUrl":"https://shared.akamai.steamstatic.com/store_item_assets/steam/apps/1809540/header.jpg?t=1762838904","genres":"액션, 어드벤처, 인디","categories":"싱글 플레이어, Steam 도전 과제, 컨트롤러 완벽 지원, 색상 대체, 음량 개별 조정, 난이도 조정, 키보드 전용 옵션, 스테레오 사운드, Steam Cloud, Steam 순위표, 가족 공유","tags":null,"shortDescription":"는 도교적 요소가 가미된 타오 펑크(Tao-punk)와 상고 신화를 결합한 2D 액션 플랫포머 게임입니다. 핸드 드로잉 방식으로 표현된 독특한 타오 펑크 세계를 배경으로 패링 메커니즘이 돋보이는 스피디하고 호쾌한 전투가 펼쳐집니다.","shortDescriptionEn":"Nine Sols is a lore rich, hand-drawn 2D action-platformer featuring Sekiro-inspired deflection focused combat. Embark on a journey of eastern fantasy, explore the land once home to an ancient alien race, and follow a vengeful hero’s quest to slay the 9 Sols, formidable rulers of this forsaken realm.","reviewSummary":"Overwhelmingly Positive | 96% | 18,318 reviews","reviewPercent":96,"reviewCount":18318,"developers":"RedCandleGames","publishers":"RedCandleGames","dlcCount":2,"appType":null,"koreanSupport":true,"koreanSubtitle":true,"koreanAudio":false,"englishSupport":true,"englishSubtitle":true,"englishAudio":false,"releaseStatus":"RELEASED","releaseDate":"2024-01-01T00:00:00.000Z","releaseDateRaw":"28 May, 2024"},"dlcList":[],"latest":{"currency":"KRW","price":3200000,"basePrice":3200000,"discountPercent":0,"discountEnd":null,"recordedAt":"2026-01-10T01:21:53.977Z"},"history":[],"playerHistory":[],"playerLatest":null,"stats":{"average":3200000,"allTimeLow":3200000,"basePriceLow":3200000,"sixMonthLow":3200000},"reviewHighlights":[{"text":"그냥 럭키 퍼리 할나인줄 알았는데.. 게임이 아니라 예술을 만들어놨네.. 하.. 이게 야스가 아니면 뭐임..","votes":12},{"text":"실크송의 여운을 잊게 해주는 갓겜 메트로배니아로서 맵 디자인과 탐험은 아쉽지만 패링과 보스전은 모든 액션 게임을 압도하는 수준","votes":6}]}