{"game":{"appId":259381,"name":"PAYDAY 2: Gage Mod Courier","capsuleUrl":"https://shared.akamai.steamstatic.com/store_item_assets/steam/apps/259381/header.jpg?t=1756106376","genres":"액션, RPG","categories":"싱글 플레이어, 멀티플레이어, 협동, 다운로드 가능한 콘텐츠, Steam 도전 과제, 컨트롤러 완벽 지원, Steam 트레이딩 카드, 가족 공유","tags":null,"shortDescription":"The Gage Mod Courier DLC is the sixth DLC for PAYDAY 2. It allows players to act as a courier for Gage the arms dealer, picking up packages containing mods that are scattered all over D.C. The DLC introduces no less than 28 new weapon modifications for the player to tinker with.","shortDescriptionEn":"The Gage Mod Courier DLC is the sixth DLC for PAYDAY 2. It allows players to act as a courier for Gage the arms dealer, picking up packages containing mods that are scattered all over D.C. The DLC introduces no less than 28 new weapon modifications for the player to tinker with.","reviewSummary":null,"reviewPercent":null,"reviewCount":null,"developers":"OVERKILL - a Starbreeze Studio.","publishers":"Starbreeze Publishing AB","dlcCount":null,"appType":"dlc","koreanSupport":false,"koreanSubtitle":false,"koreanAudio":false,"englishSupport":true,"englishSubtitle":true,"englishAudio":true,"releaseStatus":"RELEASED","releaseDate":"2014-04-10T00:00:00.000Z","releaseDateRaw":"10 Apr, 2014"},"dlcList":[],"latest":{"currency":"KRW","price":110000,"basePrice":110000,"discountPercent":0,"discountEnd":null,"recordedAt":"2026-01-11T05:18:51.494Z"},"history":[],"playerHistory":[],"playerLatest":null,"stats":{"average":null,"allTimeLow":110000,"basePriceLow":110000,"sixMonthLow":110000},"reviewHighlights":[]}