{"game":{"appId":2887360,"name":"戀戀寶島～雨港再世奇緣～","capsuleUrl":"https://shared.akamai.steamstatic.com/store_item_assets/steam/apps/2887360/58f9bc4d687511c34ab7906fb17ac3d3addd9176/header.jpg?t=1759185750","genres":"어드벤처, 캐주얼, 인디","categories":"싱글 플레이어, 가족 공유","shortDescription":"『戀戀寶島～雨港再世奇緣篇～』 這是一個以現實世界的『台灣』為舞台的\"架空平行世界\" 一款單線單結局的日式文字冒險遊戲。 以架空的台灣寶島基隆市為主要場景，著名都市傳說娜娜鬼屋為開端。 融合了戀愛，靈異，美食，架空歷史的絕妙組合。 演繹Boy Meets Girl的戀愛喜劇。","shortDescriptionEn":"『戀戀寶島～雨港再世奇緣篇～』 這是一個以現實世界的『台灣』為舞台的\"架空平行世界\" 一款單線單結局的日式文字冒險遊戲。 以架空的台灣寶島基隆市為主要場景，著名都市傳說娜娜鬼屋為開端。 融合了戀愛，靈異，美食，架空歷史的絕妙組合。 演繹Boy Meets Girl的戀愛喜劇。","reviewSummary":null,"reviewPercent":null,"reviewCount":null,"developers":"TUKUMO Production","publishers":"TUKUMO Production","dlcCount":null,"koreanSupport":false,"koreanSubtitle":false,"koreanAudio":false,"englishSupport":false,"englishSubtitle":false,"englishAudio":false,"releaseStatus":"UPCOMING","releaseDate":"2026-01-01T00:00:00.000Z","releaseDateRaw":"March 2026"},"latest":null,"history":[],"playerHistory":[],"playerLatest":null,"stats":{"average":null,"allTimeLow":null,"basePriceLow":null,"sixMonthLow":null},"reviewHighlights":[]}