{"game":{"appId":3014080,"name":"The Hundred Line -Last Defense Academy-","capsuleUrl":"https://shared.akamai.steamstatic.com/store_item_assets/steam/apps/3014080/header.jpg?t=1763608121","genres":"어드벤처, 시뮬레이션","categories":"싱글 플레이어, Steam 도전 과제, 컨트롤러 완벽 지원, Steam 트레이딩 카드, Steam Cloud, 가족 공유","tags":null,"shortDescription":"코다카 카즈타카와 우치코시 코타로가 처음으로 손을 잡고 선사하는 궁극의 어드벤처 게임! 기괴한 괴물로부터 100일간 학교를 지켜야 하는 사명을 짊어진 15명의 학생. 이들은 과연 생존을 넘어서서 이면에 숨겨진 진실을 파헤칠 수 있을까요?","shortDescriptionEn":"Kazutaka Kodaka and Kotaro Uchikoshi join forces for the first time to deliver the ULTIMATE adventure game! 15 students are tasked with defending a school from grotesque monsters for 100 days. Can they make it to the end? And will they survive long enough to uncover the truth?","reviewSummary":"Very Positive | 95% | 3,693 reviews","reviewPercent":95,"reviewCount":3693,"developers":"Too Kyo Games, Media.Vision Inc.","publishers":"Aniplex Inc.","dlcCount":2,"appType":"game","koreanSupport":false,"koreanSubtitle":false,"koreanAudio":false,"englishSupport":true,"englishSubtitle":true,"englishAudio":true,"releaseStatus":"RELEASED","releaseDate":"2025-04-23T00:00:00.000Z","releaseDateRaw":"23 Apr, 2025"},"dlcList":[],"latest":{"currency":"KRW","price":4886000,"basePrice":6980000,"discountPercent":30,"discountEnd":"2026-01-19T14:59:59.000Z","recordedAt":"2026-01-11T03:05:55.219Z"},"history":[],"playerHistory":[],"playerLatest":null,"stats":{"average":4886000,"allTimeLow":4886000,"basePriceLow":6980000,"sixMonthLow":4886000},"reviewHighlights":[{"text":"very Refreshing ^^","votes":0}]}