{"game":{"appId":3046600,"name":"Onimusha 2: Samurai's Destiny","capsuleUrl":"https://shared.akamai.steamstatic.com/store_item_assets/steam/apps/3046600/header.jpg?t=1763712388","genres":"액션","categories":"싱글 플레이어, Steam 도전 과제, 컨트롤러 완벽 지원, Steam 트레이딩 카드, Steam Cloud, 가족 공유","tags":null,"shortDescription":"되살아나는 사랑과 슬픔, 그리고 베는 손맛. 고해상도 그래픽, 현행 하드웨어에 맞춰 튜닝된 조작감. 새로운 「귀무자2」로 다시 태어난다! 통쾌한 필살기 「일섬」. 중후하고 하드보일드한 스토리. 전국 서바이벌 액션의 새로운 길을 개척한 본작을 체감하자!","shortDescriptionEn":"Reclaim your destiny. Onimusha 2: Samurai's Destiny returns with higher resolution graphics and modernised controls to perform issen critical counter attacks and intense swordplay. Experience this dramatic revenge story set in Feudal Japan.","reviewSummary":"Very Positive | 89% | 292 reviews","reviewPercent":89,"reviewCount":292,"developers":"CAPCOM Co., Ltd.","publishers":"CAPCOM Co., Ltd.","dlcCount":1,"appType":null,"koreanSupport":true,"koreanSubtitle":true,"koreanAudio":false,"englishSupport":true,"englishSubtitle":true,"englishAudio":true,"releaseStatus":"RELEASED","releaseDate":"2025-01-01T00:00:00.000Z","releaseDateRaw":"22 May, 2025"},"dlcList":[],"latest":{"currency":"KRW","price":2262000,"basePrice":3480000,"discountPercent":35,"discountEnd":null,"recordedAt":"2026-01-10T01:21:53.977Z"},"history":[],"playerHistory":[],"playerLatest":null,"stats":{"average":2262000,"allTimeLow":2262000,"basePriceLow":3480000,"sixMonthLow":2262000},"reviewHighlights":[{"text":"PS2 시절 정말 재밌게 했던 겜^^ 추억삼아 구매 ㅋㅋ","votes":10},{"text":"팬들 사이에선 명작이라 불리는게 2탄인데 난 갠적으로 일탄 삼탄이 젤 재밌음","votes":3}]}