{"game":{"appId":3501210,"name":"Menhera & Troll","capsuleUrl":"https://shared.akamai.steamstatic.com/store_item_assets/steam/apps/3501210/441fb3381a65338d1276f324004744bbbff85704/header.jpg?t=1762362316","genres":"어드벤처, 인디, 시뮬레이션","categories":"싱글 플레이어, 컨트롤러 완벽 지원, 가족 공유","shortDescription":"키보드 워리어들이 사실 미소녀였다면? 심리학과 대학원생이 되어 그녀들의 마음을 치유해 보세요. 단, 그녀들이 멘헤라 & 트롤이라는 사실을 잊지 마세요! 결코 그녀들은 평범하지 않습니다.","shortDescriptionEn":"What if the keyboard warriors were actually beautiful girls? Become a psychology graduate student and try to heal their hearts. But don’t forget—they are Menhera and trolls! These girls are anything but ordinary.","reviewSummary":null,"reviewPercent":null,"reviewCount":null,"developers":"nugem studio","publishers":"nugem studio","dlcCount":null,"koreanSupport":true,"koreanSubtitle":true,"koreanAudio":false,"englishSupport":true,"englishSubtitle":true,"englishAudio":false,"releaseStatus":"UPCOMING","releaseDate":"2026-01-01T00:00:00.000Z","releaseDateRaw":"Q1 2026"},"latest":null,"history":[],"playerHistory":[],"playerLatest":null,"stats":{"average":null,"allTimeLow":null,"basePriceLow":null,"sixMonthLow":null},"reviewHighlights":[]}