{"game":{"appId":4123580,"name":"Strikers 1945 2","capsuleUrl":"https://shared.akamai.steamstatic.com/store_item_assets/steam/apps/4123580/c3d4c9b491e80edf1136e5ff581b88160756b867/header.jpg?t=1767624761","genres":"액션","categories":"싱글 플레이어, 멀티플레이어, 협동, 스크린 공유 및 분할 협동, 공유 및 분할 화면, Steam 도전 과제, 컨트롤러 완벽 지원, Steam 순위표, Remote Play Together, 가족 공유","shortDescription":"일반부터 매니아까지 폭넓은 고객층이 안심하고 플레이할 수 있는 사이쿄 계열 시스템에, 연사 레벨 3단계 강화의 신시스템을 탑재하여 전략성이 더욱 높아졌습니다. 아직 플레이하지 않은 분들도 꼭 플레이해 보세요.","shortDescriptionEn":"The Saikyo-style system, trusted by players from casual gamers to hardcore enthusiasts, now features a new three-stage charge shot enhancement system, significantly boosting strategic depth. If you haven't played it yet, we urge you to give it a try.","reviewSummary":null,"reviewPercent":null,"reviewCount":null,"developers":"Zerodiv","publishers":"KMBOX","dlcCount":null,"koreanSupport":true,"koreanSubtitle":true,"koreanAudio":false,"englishSupport":true,"englishSubtitle":true,"englishAudio":false,"releaseStatus":"RELEASED","releaseDate":"2026-01-01T00:00:00.000Z","releaseDateRaw":"5 Jan, 2026"},"latest":{"currency":"KRW","price":770000,"basePrice":1100000,"discountPercent":30,"discountEnd":"2026-01-13T14:59:59.000Z","recordedAt":"2026-01-10T01:21:53.977Z"},"history":[],"playerHistory":[],"playerLatest":null,"stats":{"average":770000,"allTimeLow":770000,"basePriceLow":1100000,"sixMonthLow":770000},"reviewHighlights":[]}