{"game":{"appId":47932,"name":"The Sims™ 3 Showtime","capsuleUrl":"https://shared.akamai.steamstatic.com/store_item_assets/steam/apps/47932/header.jpg?t=1738947850","genres":"시뮬레이션","categories":"싱글 플레이어, 다운로드 가능한 콘텐츠, 가족 공유","tags":null,"shortDescription":"Venture into the new world of Starlight Shores and play out a rags-to-riches story with your Sims as they become superstar singers, acrobats, and magicians, or even moonlight as a DJ. Watch your Sims rise to fame—or go down in flames as they perform on stage in front of cheering crowds in all new ve","shortDescriptionEn":"Venture into the new world of Starlight Shores and play out a rags-to-riches story with your Sims as they become superstar singers, acrobats, and magicians, or even moonlight as a DJ. Watch your Sims rise to fame—or go down in flames as they perform on stage in front of cheering crowds in all new ve","reviewSummary":null,"reviewPercent":null,"reviewCount":null,"developers":"The Sims Studio","publishers":"Electronic Arts","dlcCount":null,"appType":"dlc","koreanSupport":true,"koreanSubtitle":true,"koreanAudio":false,"englishSupport":true,"englishSubtitle":true,"englishAudio":false,"releaseStatus":"RELEASED","releaseDate":"2012-03-08T00:00:00.000Z","releaseDateRaw":"8 Mar, 2012"},"dlcList":[],"latest":{"currency":"KRW","price":2200000,"basePrice":2200000,"discountPercent":0,"discountEnd":null,"recordedAt":"2026-01-11T05:18:51.494Z"},"history":[],"playerHistory":[],"playerLatest":null,"stats":{"average":null,"allTimeLow":2200000,"basePriceLow":2200000,"sixMonthLow":2200000},"reviewHighlights":[]}