{"game":{"appId":586350,"name":"UBERMOSH:WRAITH","capsuleUrl":"https://shared.akamai.steamstatic.com/store_item_assets/steam/apps/586350/header.jpg?t=1699491375","genres":"액션, 인디","categories":"싱글 플레이어, Steam 도전 과제, 컨트롤러 완벽 지원, Steam 트레이딩 카드, 가족 공유","shortDescription":"UBERMOSH:WRAITH is the fourth volume of the arcade series UBERMOSH.","shortDescriptionEn":"UBERMOSH:WRAITH is the fourth volume of the arcade series UBERMOSH.","reviewSummary":"Very Positive | 91% | 377 reviews","reviewPercent":91,"reviewCount":377,"developers":"Walter Machado","publishers":"Walter Machado","dlcCount":null,"koreanSupport":true,"koreanSubtitle":true,"koreanAudio":true,"englishSupport":true,"englishSubtitle":true,"englishAudio":true,"releaseStatus":"RELEASED","releaseDate":"2017-01-01T00:00:00.000Z","releaseDateRaw":"29 Jan, 2017"},"latest":{"currency":"KRW","price":55000,"basePrice":550000,"discountPercent":90,"discountEnd":"2026-01-20T14:59:59.000Z","recordedAt":"2026-01-10T05:17:23.579Z"},"history":[],"playerHistory":[],"playerLatest":null,"stats":{"average":55000,"allTimeLow":55000,"basePriceLow":550000,"sixMonthLow":55000},"reviewHighlights":[{"text":"UBERMOSH:WRAITH 픽셀류의 뱀파이어 서바이버 류의 90초간 외계인들의 공격에서 살아남는 게임. 킬링타임용으로는 좋지만 조잡한 픽셀그래픽에 과도한 탄막으로 인해 눈에 피로도가 상당하다 너무 조잡하다.","votes":12}]}