{"game":{"appId":754520,"name":"Animals Memory","capsuleUrl":"https://shared.akamai.steamstatic.com/store_item_assets/steam/apps/754520/header.jpg?t=1546693591","genres":"캐주얼, 인디","categories":"싱글 플레이어, Steam 도전 과제, 가족 공유","tags":null,"shortDescription":"Animals Memory - is a card game that tests your memory. The objective of the game is tomatch cards with the same card picture.","shortDescriptionEn":"Animals Memory - is a card game that tests your memory. The objective of the game is tomatch cards with the same card picture.","reviewSummary":"Positive | 81% | 36 reviews","reviewPercent":81,"reviewCount":36,"developers":"Laush Dmitriy Sergeevich","publishers":"Laush Dmitriy Sergeevich","dlcCount":null,"appType":null,"koreanSupport":false,"koreanSubtitle":false,"koreanAudio":false,"englishSupport":true,"englishSubtitle":true,"englishAudio":false,"releaseStatus":"RELEASED","releaseDate":"2017-01-01T00:00:00.000Z","releaseDateRaw":"20 Dec, 2017"},"dlcList":[],"latest":{"currency":"KRW","price":78000,"basePrice":560000,"discountPercent":86,"discountEnd":"2026-01-13T14:59:59.000Z","recordedAt":"2026-01-10T05:17:23.579Z"},"history":[],"playerHistory":[],"playerLatest":null,"stats":{"average":78000,"allTimeLow":78000,"basePriceLow":560000,"sixMonthLow":78000},"reviewHighlights":[{"text":"다양한 동물 친구들의 짝을 찾아주자. 1레벨을 리스타트로 35번만 반복하면 도전과제 올클리어 가능.","votes":55},{"text":"이게 왜 정가가 5,500원인가 의문이 들긴 하지만. 할인 할 때 사시면 가성비 도전과제 게임이 됩니다. 1레벨만 깨셔도 도전과제 클리어가 됩니다. 어디까지나 도전과제용이기 때문에 게임성을 봤을땐 비추.","votes":9}]}